black_holes/__init__.py
black_holes/core.py
black_holes/models.py
black_holes/prefabs.py
black_holes-0.0.32.dist-info/METADATA
black_holes-0.0.32.dist-info/WHEEL
black_holes-0.0.32.dist-info/top_level.txt
black_holes-0.0.32.dist-info/RECORD
