Metadata-Version: 2.1
Name: black-holes
Version: 0.0.32
Summary: Easy way to handle platform secrets.
Home-page: https://gitlab.com/JoseSalgado1024/black-holes
Author: Jose A. Salgado
Author-email: jose.salgado.wrk@gmail.com
License: UNKNOWN
Platform: UNKNOWN
Classifier: Programming Language :: Python :: 3
Classifier: License :: OSI Approved :: MIT License
Classifier: Operating System :: OS Independent
Requires-Dist: Crypto
Requires-Dist: python-consul (==1.1.0)
Requires-Dist: peewee (==3.9.2)
Requires-Dist: pycryptodome (==3.7.3)
